mfl/__init__.py
myfantasyleague-0.1.dist-info/DESCRIPTION.rst
myfantasyleague-0.1.dist-info/METADATA
myfantasyleague-0.1.dist-info/RECORD
myfantasyleague-0.1.dist-info/WHEEL
myfantasyleague-0.1.dist-info/metadata.json
myfantasyleague-0.1.dist-info/top_level.txt
